{
  "inhouse_forex": {
    "rate_tiering": {
      "rows": [
        {
          "RATE_TIERING_ID": "RT-UUID-001",
          "CURRENCY_ISO_CODE": "USD",
          "MIN_AMOUNT": "0",
          "MAX_AMOUNT": "10000",
          "TIERING_GROUP": "RETAIL",
          "IS_DELETED": "0",
          "CREATED_BY": "SYSTEM",
          "CREATED_TIME": "2024-01-01 00:00:00",
          "UPDATED_BY": "SYSTEM",
          "UPDATED_TIME": "2024-01-01 00:00:00"
        },
        {
          "RATE_TIERING_ID": "RT-UUID-002",
          "CURRENCY_ISO_CODE": "USD",
          "MIN_AMOUNT": "10000",
          "MAX_AMOUNT": "50000",
          "TIERING_GROUP": "RETAIL",
          "IS_DELETED": "0",
          "CREATED_BY": "SYSTEM",
          "CREATED_TIME": "2024-01-01 00:00:00",
          "UPDATED_BY": "SYSTEM",
          "UPDATED_TIME": "2024-01-01 00:00:00"
        }
      ]
    },
    "other_table": {
      "rows": [
        {
          "OTHER_TABLE_ID": "OT-UUID-001",
          "CURRENCY_ISO_CODE": "USD",
          "IS_DELETED": "0",
          "CREATED_BY": "SYSTEM",
          "CREATED_TIME": "2024-01-01 00:00:00",
          "UPDATED_BY": "SYSTEM",
          "UPDATED_TIME": "2024-01-01 00:00:00"
        }
      ]
    }
  }
}
